moremodule/Computer.py
moremodule/Keyboard.py
moremodule/Mouse.py
moremodule/Randomize.py
moremodule/WaitingScript.py
moremodule/__init__.py
moremodule-0.1.5.dist-info/METADATA
moremodule-0.1.5.dist-info/WHEEL
moremodule-0.1.5.dist-info/top_level.txt
moremodule-0.1.5.dist-info/RECORD
