Metadata-Version: 2.4
Name: moremodule
Version: 0.1.5
Summary: An small modules
Author-email: Itadamfan <vusminhklangcitend72727@gmail.com>
Requires-Python: >=3.8
